{
  "chinese_words": [
    {
      "chinese": "学习",
      "pinyin": "xuexi",
      "english": "study",
      "example": "我要学习",
      "category": "简单",
      "id": "custom_1783997986641_cl9sag",
      "createdAt": 1783997986641
    },
    {
      "chinese": "黄色",
      "pinyin": "huangse",
      "english": "yellow",
      "example": "黄色的香蕉",
      "category": "简单",
      "id": "custom_1783998051008_ma3zhb",
      "createdAt": 1783998051008
    }
  ],
  "chinese_favorites": [],
  "chinese_wrong_words": [],
  "chinese_known_words": [
    {
      "chinese": "学习",
      "pinyin": "xuexi",
      "english": "study",
      "example": "我要学习中文",
      "category": "简单",
      "id": "custom_1783925174196_6lto3j",
      "createdAt": 1783925174196,
      "knownAt": 1783934936444
    }
  ],
  "cl_streak_dates": [
    "2026-07-14"
  ],
  "cl_daily_goal": 15
}